Workbook

Sheet Model
A1: Gemini Space Station, Inc. (GEMI) — $4.065 — repaired model (v2)
A2: Green cells were placeholder text in v1 and are now formulas. Yellow cells are new inputs. Operating drivers are unchanged from v1 so the only differences are structural.
A4: USD millions unless noted | B4: 2023 | C4: 2024 | D4: 2025 | E4: 2026 | F4: 2027 | G4: 2028 | H4: 2029 | I4: 2030
A5: Operating drivers
A6: Exchange volume ($B) | D6: 52.7 | E6: 16.8 | F6: 24 | G6: 30 | H6: 34 | I6: 38
A7: Exchange take rate | B7: =IF(N(B6)=0,"",B13/B6*10) | C7: =IF(N(C6)=0,"",C13/C6*10) | D7: =IF(N(D6)=0,"",D13/D6*10) -> 17.727894 | E7: =IF(N(E6)=0,"",E13/E6*10) -> 28.452381 | F7: =IF(N(F6)=0,"",F13/F6*10) -> 27 | G7: =IF(N(G6)=0,"",G13/G6*10) -> 26 | H7: =IF(N(H6)=0,"",H13/H6*10) -> 25 | I7: =IF(N(I6)=0,"",I13/I6*10) -> 24
A8: Prediction notional ($M, two-sided) | D8: 2.8 | E8: 745 | F8: 1150 | G8: 1700 | H8: 2200 | I8: 2700
A9: Prediction take rate | B9: =IF(N(B8)=0,"",B15/B8*10000) | C9: =IF(N(C8)=0,"",C15/C8*10000) | D9: =IF(N(D8)=0,"",D15/D8*10000) -> 0 | E9: =IF(N(E8)=0,"",E15/E8*10000) -> 33.557047 | F9: =IF(N(F8)=0,"",F15/F8*10000) -> 31.304348 | G9: =IF(N(G8)=0,"",G15/G8*10000) -> 30 | H9: =IF(N(H8)=0,"",H15/H8*10000) -> 29.090909 | I9: =IF(N(I8)=0,"",I15/I8*10000) -> 28.148148
A10: Card volume ($B) | E10: 4.3 | F10: 5.5 | G10: 6.8 | H10: 8 | I10: 9.2
A11: Monthly transacting users (k) | D11: 601 | E11: 600 | F11: 660 | G11: 730 | H11: 800 | I11: 870
A12: Revenue
A13: Exchange revenue | D13: 93.426 | E13: 47.8 | F13: 64.8 | G13: 78 | H13: 85 | I13: 91.2
A14: OTC revenue | D14: 4.013 | E14: 17.6 | F14: 18 | G14: 21 | H14: 24 | I14: 27
A15: Prediction revenue | D15: 0 | E15: 2.5 | F15: 3.6 | G15: 5.1 | H15: 6.4 | I15: 7.6
A16: Other transaction revenue | D16: 0.581 | E16: 0.8 | F16: 0.9 | G16: 1 | H16: 1.1 | I16: 1.2
A17: Transaction revenue | B17: =IF(COUNT(B13:B16)=0,"",SUM(B13:B16)) | C17: =IF(COUNT(C13:C16)=0,"",SUM(C13:C16)) | D17: =IF(COUNT(D13:D16)=0,"",SUM(D13:D16)) -> 98.02 | E17: =IF(COUNT(E13:E16)=0,"",SUM(E13:E16)) -> 68.7 | F17: =IF(COUNT(F13:F16)=0,"",SUM(F13:F16)) -> 87.3 | G17: =IF(COUNT(G13:G16)=0,"",SUM(G13:G16)) -> 105.1 | H17: =IF(COUNT(H13:H16)=0,"",SUM(H13:H16)) -> 116.5 | I17: =IF(COUNT(I13:I16)=0,"",SUM(I13:I16)) -> 127
A18: Service revenue | D18: 64.639 | E18: 88.2 | F18: 105 | G18: 124 | H18: 148 | I18: 178
A19: Other income | D19: 16.913 | E19: 17.2 | F19: 18 | G19: 21 | H19: 25 | I19: 30
A20: Sales | B20: =IF(COUNT(B17,B18,B19)=0,"",B17+B18+B19) | C20: =IF(COUNT(C17,C18,C19)=0,"",C17+C18+C19) | D20: =IF(COUNT(D17,D18,D19)=0,"",D17+D18+D19) -> 179.572 | E20: =IF(COUNT(E17,E18,E19)=0,"",E17+E18+E19) -> 174.1 | F20: =IF(COUNT(F17,F18,F19)=0,"",F17+F18+F19) -> 210.3 | G20: =IF(COUNT(G17,G18,G19)=0,"",G17+G18+G19) -> 250.1 | H20: =IF(COUNT(H17,H18,H19)=0,"",H17+H18+H19) -> 289.5 | I20: =IF(COUNT(I17,I18,I19)=0,"",I17+I18+I19) -> 335
A21: Sales Y/Y | C21: =IFERROR(IF(OR(N(B20)=0,N(C20)=0),"",C20/B20-1),"") | D21: =IFERROR(IF(OR(N(C20)=0,N(D20)=0),"",D20/C20-1),"") | E21: =IFERROR(IF(OR(N(D20)=0,N(E20)=0),"",E20/D20-1),"") -> -0.030472457 | F21: =IFERROR(IF(OR(N(E20)=0,N(F20)=0),"",F20/E20-1),"") -> 0.20792648 | G21: =IFERROR(IF(OR(N(F20)=0,N(G20)=0),"",G20/F20-1),"") -> 0.18925345 | H21: =IFERROR(IF(OR(N(G20)=0,N(H20)=0),"",H20/G20-1),"") -> 0.15753699 | I21: =IFERROR(IF(OR(N(H20)=0,N(I20)=0),"",I20/H20-1),"") -> 0.15716753
A22: Prediction % of Sales | B22: =IFERROR(IF(N(B20)=0,"",B15/B20),"") | C22: =IFERROR(IF(N(C20)=0,"",C15/C20),"") | D22: =IFERROR(IF(N(D20)=0,"",D15/D20),"") -> 0 | E22: =IFERROR(IF(N(E20)=0,"",E15/E20),"") -> 0.014359563 | F22: =IFERROR(IF(N(F20)=0,"",F15/F20),"") -> 0.017118402 | G22: =IFERROR(IF(N(G20)=0,"",G15/G20),"") -> 0.020391843 | H22: =IFERROR(IF(N(H20)=0,"",H15/H20),"") -> 0.022107081 | I22: =IFERROR(IF(N(I20)=0,"",I15/I20),"") -> 0.022686567
A23: Costs and earnings
A24: Opex | D24: 525.228 | E24: 508 | F24: 495 | G24: 490 | H24: 495 | I24: 500
A25: Opex % | B25: =IFERROR(IF(N(B20)=0,"",B24/B20),"") | C25: =IFERROR(IF(N(C20)=0,"",C24/C20),"") | D25: =IFERROR(IF(N(D20)=0,"",D24/D20),"") -> 2.9248881 | E25: =IFERROR(IF(N(E20)=0,"",E24/E20),"") -> 2.9178633 | F25: =IFERROR(IF(N(F20)=0,"",F24/F20),"") -> 2.3537803 | G25: =IFERROR(IF(N(G20)=0,"",G24/G20),"") -> 1.9592163 | H25: =IFERROR(IF(N(H20)=0,"",H24/H20),"") -> 1.7098446 | I25: =IFERROR(IF(N(I20)=0,"",I24/I20),"") -> 1.4925373
A26: EBIT | B26: =IF(N(B20)=0,"",B20-B24) | C26: =IF(N(C20)=0,"",C20-C24) | D26: =IF(N(D20)=0,"",D20-D24) -> -345.656 | E26: =IF(N(E20)=0,"",E20-E24) -> -333.9 | F26: =IF(N(F20)=0,"",F20-F24) -> -284.7 | G26: =IF(N(G20)=0,"",G20-G24) -> -239.9 | H26: =IF(N(H20)=0,"",H20-H24) -> -205.5 | I26: =IF(N(I20)=0,"",I20-I24) -> -165
A27: EBIT % | B27: =IFERROR(IF(N(B20)=0,"",B26/B20),"") | C27: =IFERROR(IF(N(C20)=0,"",C26/C20),"") | D27: =IFERROR(IF(N(D20)=0,"",D26/D20),"") -> -1.9248881 | E27: =IFERROR(IF(N(E20)=0,"",E26/E20),"") -> -1.9178633 | F27: =IFERROR(IF(N(F20)=0,"",F26/F20),"") -> -1.3537803 | G27: =IFERROR(IF(N(G20)=0,"",G26/G20),"") -> -0.95921631 | H27: =IFERROR(IF(N(H20)=0,"",H26/H20),"") -> -0.70984456 | I27: =IFERROR(IF(N(I20)=0,"",I26/I20),"") -> -0.49253731
A28: Depreciation | D28: 30.723 | E28: 30 | F28: 32 | G28: 33 | H28: 34 | I28: 35
A29: EBITDA | B29: =IF(N(B26)=0,"",B26+B28) | C29: =IF(N(C26)=0,"",C26+C28) | D29: =IF(N(D26)=0,"",D26+D28) -> -314.933 | E29: =IF(N(E26)=0,"",E26+E28) -> -303.9 | F29: =IF(N(F26)=0,"",F26+F28) -> -252.7 | G29: =IF(N(G26)=0,"",G26+G28) -> -206.9 | H29: =IF(N(H26)=0,"",H26+H28) -> -171.5 | I29: =IF(N(I26)=0,"",I26+I28) -> -130
A30: SBC | D30: 84.956 | E30: 88 | F30: 85 | G30: 82 | H30: 80 | I30: 78
A31: EBITDA ex SBC | B31: =IF(N(B29)=0,"",B29+B30) | C31: =IF(N(C29)=0,"",C29+C30) | D31: =IF(N(D29)=0,"",D29+D30) -> -229.977 | E31: =IF(N(E29)=0,"",E29+E30) -> -215.9 | F31: =IF(N(F29)=0,"",F29+F30) -> -167.7 | G31: =IF(N(G29)=0,"",G29+G30) -> -124.9 | H31: =IF(N(H29)=0,"",H29+H30) -> -91.5 | I31: =IF(N(I29)=0,"",I29+I30) -> -52
A32: Net Income | D32: -582.813 | E32: -367 | F32: -310 | G32: -265 | H32: -230 | I32: -190
A33: EPS ($) | D33: -15.52 | E33: -2.97 | F33: -2.42 | G33: -2.02 | H33: -1.72 | I33: -1.39
A34: Implied diluted shares (M) | B34: =IFERROR(IF(N(B33)=0,"",B32/B33),"") | C34: =IFERROR(IF(N(C33)=0,"",C32/C33),"") | D34: =IFERROR(IF(N(D33)=0,"",D32/D33),"") -> 37.552384 | E34: =IFERROR(IF(N(E33)=0,"",E32/E33),"") -> 123.56902 | F34: =IFERROR(IF(N(F33)=0,"",F32/F33),"") -> 128.09917 | G34: =IFERROR(IF(N(G33)=0,"",G32/G33),"") -> 131.18812 | H34: =IFERROR(IF(N(H33)=0,"",H32/H33),"") -> 133.72093 | I34: =IFERROR(IF(N(I33)=0,"",I32/I33),"") -> 136.69065
A35: Implied share count is a v2 addition. It shows the model already assumes roughly 124M shares in 2026 rising to 137M by 2030, consistent with 126.2M outstanding today. FY2025's 37.6M is a pre-IPO weighted average, so any growth rate computed off a 2025 per-share figure is meaningless.

Sheet EV Bridge
A1: EV bridge — Q1 2026 10-Q balance sheet
A2: v1 used a single input, Net Cash = -252.8, which equals the related-party loans line alone. It netted no cash and omitted three other debt lines. The variants below are all defensible; variant 3 feeds the scenarios because it excludes the two matched books that are not shareholder claims.
A4: Balance sheet, USD millions (Mar 31, 2026)
A5: Line | B5: Amount | C5: Treatment | D5: Why
A6: Cash and cash equivalents | B6: 215.623 | C6: Corporate cash | D6: Unencumbered. Nets against debt.
A7: Restricted cash | B7: 103.747 | C7: Excluded | D7: Not available to service claims or fund operations.
A8: Customer custodial funds | B8: 483.774 | C8: Excluded | D8: Offset by custodial funds due to customers of $483.7M. Customer money, not shareholder value.
A9: Crypto assets held | B9: 271.956 | C9: Variant 4 only | D9: Partly financed by the crypto loan lines, so crediting it in full while also counting those loans double counts.
A10: Credit card receivables pledged | B10: 183.965 | C10: Excluded with funding debt | D10: Matched book: pledged against the funding debt below.
A11: Third party loans | B11: -75.349 | C11: Debt | D11: Includes the bitcoin repurchase agreement.
A12: Related party loans | B12: -252.574 | C12: Debt | D12: The only line v1 captured.
A13: Funding debt | B13: -140.457 | C13: Excluded with pledged receivables | D13: Secured by the credit card receivables.
A14: Lease liabilities | B14: -18.764 | C14: Debt | D14: Non-current.
A16: Total debt (all four lines) | B16: =-(B11+B12+B13+B14) -> 487.144
A18: EV variants
A19: # | B19: Definition | C19: Net debt | D19: EV | E19: Note
A20: 1 | B20: v1 as delivered: cap + related-party loans only | C20: 252.574 | D20: =513+C20 -> 765.574 | E20: What the v1 scenarios were valued against.
A21: 2 | B21: cap + all debt - corporate cash | C21: 271.521 | D21: =513+C21 -> 784.521 | E21: Most literal reading.
A22: 3 | B22: variant 2, excluding the matched credit-card book | C22: 131.064 | D22: =513+C22 -> 644.064 | E22: Selected. Funding debt and pledged receivables offset each other.
A23: 4 | B23: variant 3, also crediting crypto assets held | C23: -140.892 | D23: =513+C23 -> 372.108 | E23: Most generous. Risks double counting against the crypto loans.
A25: Market cap | B25: 513
A26: Selected EV (variant 3) | B26: =D22 -> 644.064
A27: Tangible book equity | B27: 321.907
A28: Tangible book per share ($) | B28: =B27/126.2 -> 2.5507686
A30: The $803M cash claim
A31: $215.6M cash + $103.7M restricted + $483.8M customer custodial funds = $803.1M. The custodial component is offset almost exactly by $483.7M of custodial funds due to customers, and restricted cash is not available by definition. Unencumbered corporate cash is $215.6M. An asset-support argument built on the $803M figure counts customer money as shareholder value.
A35: Separately, the $372M crypto figure does not tie to the last filed balance sheet, which shows $272.0M of crypto assets held at Mar 31, 2026 and $439.6M at Dec 31, 2025. Treat $372M as unverified until the Q2 10-Q lands.

Sheet Scenarios
A1: Scenarios — 2030 estimates
A2: v1's revenue table could not compute upside because the base-year EV cell was blank, and its EPS table multiplied a negative EPS by a zero PE to produce a $0.00 target and a -100% return. Both are fixed here.
A4: EV / Sales on 2030 revenue
A5: Scenario | B5: 2030 revenue | C5: EV/Sales | D5: Implied EV | E5: Implied equity | F5: Implied price | G5: Upside
A6: Bull | B6: 470 | C6: 5 | D6: =B6*C6 -> 2350 | E6: =D6-('EV Bridge'!$B$26-513) -> 2218.936 | F6: =MAX(E6/126.2,'EV Bridge'!$B$28) -> 17.582694 | G6: =F6/4.065-1 -> 3.325386
A7: Base | B7: 335 | C7: 3 | D7: =B7*C7 -> 1005 | E7: =D7-('EV Bridge'!$B$26-513) -> 873.936 | F7: =MAX(E7/126.2,'EV Bridge'!$B$28) -> 6.9250079 | G7: =F7/4.065-1 -> 0.70356898
A8: Bear | B8: 210 | C8: 1.75 | D8: =B8*C8 -> 367.5 | E8: =D8-('EV Bridge'!$B$26-513) -> 236.436 | F8: =MAX(E8/126.2,'EV Bridge'!$B$28) -> 2.5507686 | G8: =F8/4.065-1 -> -0.37250464
A10: Implied price floors at tangible book per share, so a bear case does not print a value below the company's hard assets. Upside is measured against the $4.065 close.
A12: Why the EPS / PE table was removed
A13: v1 valued Base and Bear at EPS x PE = -1.39 x 0 = $0.00 and -2.60 x 0 = $0.00, reporting -100.0% for both. A PE multiple cannot value negative earnings, and a business carrying $456.1M of book equity and $215.6M of corporate cash is not worth zero. The Bull row was the only one doing work, and even there $0.20 x 35 = $7.00 is a PE applied to the first profitable year with no discounting. Sales-based valuation with a book floor is the defensible frame while the company is loss-making.
A18: Model versus consensus
A19: Metric | B19: Model | C19: Consensus | D19: Gap
A20: FY2026 revenue | B20: =Model!E20 -> 174.1 | C20: 193.18 | D20: =B20-C20 -> -19.08
A21: FY2026 EPS | B21: =Model!E33 -> -2.97 | C21: -2.897 | D21: =B21-C21 -> -0.073
A22: FY2030 revenue | B22: =Model!I20 -> 335 | C22: 394.15 | D22: =B22-C22 -> -59.15
A23: FY2030 EPS | B23: =Model!I33 -> -1.39 | C23: -1.775 | D23: =B23-C23 -> 0.385
A25: The model sits below consensus on revenue in both years but above it on 2030 EPS. That combination requires materially better margins than the street assumes on a smaller revenue base, which is an implicit call the v1 file never stated. Either the opex path is too optimistic or the revenue path is too conservative.

Sheet Prediction Volume
A1: Prediction volume — Gemini Titan published daily series
A2: Source: api.gemini.com/v1/prediction-markets/volume/{date}, the public surface of Titan's DCM daily publication obligation. Full daily coverage since 2025-12-15.
A4: Convention reconciliation against the Artemis warehouse series
A5: Window | B5: Public endpoint (one-sided) | C5: Artemis warehouse | D5: Ratio | E5: Children rows | F5: Read
A6: 2025-12-15 to 2025-12-31 | B6: 1387082 | C6: 2774094 | D6: 1.9999495 | E6: 0 | F6: Exactly 2x
A7: Q1 2026 | B7: 59667196 | C7: 119336290 | D7: 2.0000318 | E7: 65868534 | F7: Exactly 2x
A8: Q2 2026 | B8: 115249040 | C8: 229207575 | D8: 1.9888025 | E8: 130642065 | F8: Near 2x
A10: The December window contains only one category row and no children, yet Artemis is still exactly 2.00x. That rules out hierarchy double counting and points to a two-sided convention: Artemis counts both legs of each match, the public endpoint counts one. Revenue is unaffected because the take rate is calibrated and applied on the same basis, but any cross-venue share comparison must put all venues on one convention.
A14: Half-month run rates — the -26% claim
A15: Window | B15: Per day (one-sided) | C15: Days | D15: vs prior window
A16: Q2 2026 average | B16: 1266473 | C16: 91
A17: Jun 1-15 | B17: 1228637.6 | C17: 15
A18: Jun 16-30 | B18: 1890726.8 | C18: 15
A19: Jul 1-15 | B19: 1834617.4 | C19: 15
A20: Jul 16-28 | B20: 1394405.3 | C20: 13
A22: Comparisons
A23: Comparison | B23: Change
A24: Jul 1-15 vs Jun 1-15 | B24: 0.49321281
A25: Jul 1-15 vs Jun 16-30 | B25: -0.029676101
A26: Jul 1-15 vs Q2 average | B26: 0.44860368
A27: Jul 16-28 vs Jul 1-15 | B27: -0.23994763
A28: Jul 16-28 vs Jun 16-30 | B28: -0.26250302 | C28: matches the quoted -26%
A30: The -26% figure reconciles to Jul 16-28 versus Jun 16-30, the back half of each month, not the first half of July. Jul 1-15 was up 49% on Jun 1-15 and up 45% on the Q2 average. July as a whole ran the highest per-day volume of any month since launch. There is a real late-July deceleration and it is worth tracking, but it is the second half of the month, and the level is still above the Q2 average rather than below it.
A35: Monthly series
A36: Month | B36: Total (one-sided) | C36: Per day | D36: Days
A37: 2026-04 | B37: 30261358 | C37: 1008711.9 | D37: 30
A38: 2026-05 | B38: 38197216 | C38: 1232168.3 | D38: 31
A39: 2026-06 | B39: 46790466 | C39: 1559682.2 | D39: 30
A40: 2026-07 (1-28) | B40: 45646530 | C40: 1630233.2 | D40: 28

Sheet Review
A1: Review of the v1 simple model
A2: Blocking means the v1 file does not produce the number it claims to. Material means the number computes but the conclusion drawn from it does not hold. Confirmed means it was checked against an independent source and stands.
A4: Severity | B4: Finding | C4: Evidence | D4: Resolution in v2
A5: Blocking | B5: Sales row was placeholder text | C5: Model!B18:I18 held the string "—", so Sales never computed. Every cell referencing it errored: EV/Sales, Opex %, EBIT, EBIT %, EBITDA, Sales Y/Y and all CAGRs. | D5: Fixed. Sales = transaction + service + other income.
A6: Blocking | B6: Revenue scenarios had no upside column | C6: Market cap and net cash were populated only for 2026-2030, leaving the base-year EV cell empty, so every Ups/Downs formula divided by zero. The model's headline output was missing. | D6: Fixed. Scenarios now reference an explicit selected-EV cell. Bull is +207% on EV.
A7: Blocking | B7: EPS / PE table is analytically void | C7: Base -1.39 x 0 PE = $0.00 and Bear -2.60 x 0 = $0.00, both reported as -100%. A PE cannot value negative earnings, and the company holds $456.1M of book equity and $215.6M of corporate cash. | D7: Removed. Replaced with EV/Sales to equity value, floored at tangible book per share.
A8: Blocking | B8: Net Cash input is one debt line, not net cash | C8: -252.8 equals the related-party loans line ($252.574M) alone. It nets no cash and omits third-party loans ($75.3M), funding debt ($140.5M) and leases ($18.8M). | D8: Fixed. New EV Bridge sheet builds four variants off the Q1 2026 balance sheet; variant 3 is selected.
A9: Material | B9: The $803M cash claim counts customer money | C9: $803.1M = cash $215.6M + restricted $103.7M + customer custodial funds $483.8M. The custodial line is offset by $483.7M of custodial funds due to customers. Unencumbered corporate cash is $215.6M. | D9: Documented on the EV Bridge sheet. The asset-support argument does not survive as stated.
A10: Material | B10: The -26% July prediction-volume claim is the wrong window | C10: -26.3% reconciles to Jul 16-28 versus Jun 16-30. Jul 1-15 was +49.3% on Jun 1-15 and +44.9% on the Q2 average; July ran the highest per-day volume since launch. | D10: Corrected on the Prediction Volume sheet. The late-July deceleration is real; the label is not.
A11: Material | B11: The bps share series cannot be reconciled | C11: Gemini share of three-venue notional is quoted at 36.35 / 20.46 / 9.29 bps for May / Jun / Jul days 1-15. Holding those shares against actual Gemini volume implies the three-venue denominator grew from $12.5B to $59.2B in two months, a 4.7x increase, against the note's own claim that Kalshi and Polymarket grew 63%. | D11: Flagged. Either the Gemini numerator is truncated for July or the venues are on mixed conventions. Needs a rebuild before the share-loss conclusion can be used.
A12: Material | B12: Two-sided versus one-sided volume convention is undeclared | C12: The warehouse series is exactly 2.00x the public endpoint, including in a December window with no subcategory rows, so it counts both legs of each match. Revenue is unaffected, but the 34 bps take rate is half the one-sided equivalent of 74 bps, which changes how it reads against Kalshi at 102-119 bps. | D12: Documented. Cross-venue comparisons must normalise convention first.
A13: Material | B13: Below consensus on revenue, above it on EPS | C13: Model FY2030 revenue of $335.0M is 15.0% below consensus $394.15M, yet model EPS of -$1.39 is $0.39 better than consensus -$1.775. That is a materially better margin call on a smaller base, never stated. | D13: Surfaced in a comparison block. Reconcile the opex path or the revenue path.
A14: Minor | B14: $372M crypto does not tie to the filings | C14: The last filed balance sheet shows $272.0M of crypto assets held at Mar 31, 2026 and $439.6M at Dec 31, 2025. | D14: Flagged as unverified.
A15: Minor | B15: Take rate rows were placeholder text | C15: Exchange and prediction take rates were "—" throughout, hiding the assumption that exchange take rate steps from 17.7 bps in FY2025 to 28.5 bps in FY2026 then decays to 24.0 bps by 2030. | D15: Fixed. Both now compute in bps. The FY2026 step is supported by Q1 2026 actuals at 27.3 bps.
... A18: Confirmed | B18: Prediction materiality is right | C18: At 34 bps on $229.2M two-sided notional, Q2 prediction revenue is about $0.78M, 1.8% of a $43.8M revenue estimate and roughly $0.006 of EPS on 126.2M shares. The independent one-sided calibration gives $0.858M. | D18: No change. Both methods agree that the segment is immaterial to Q2.

Sheet Sources
A1: Sources
A3: id | B3: kind | C3: url | D3: excerpt
A4: src_wh_fy2025_pl | B4: warehouse | D4: GOLD.EQUITIES.FACT_EQUITIES_INTERNAL_FINANCIAL_METRICS, GEMI FY2025 actuals: total_revenue $179.572M, operating_expenses $525.228M, operating_income -$345.656M, net_income -$582.813M, diluted_eps -$15.52, diluted_shares 37.552M, depreciation_and_amortization $30.723M, stock_based_compensation $84.956M, investment_income_interest $11.434M, cash_from_operations -$218.108M, fcf -$220.088M.
A5: src_wh_fy2025_segments | B5: 10-K | C5: https://www.sec.gov/Archives/edgar/data/2055592/000205559226000026/R60.htm | D5: FY2025 XBRL revenue disaggregation: transaction revenue $98.020M (exchange $93.426M, OTC $4.013M, other $0.581M, prediction market not separately broken out), service revenue $64.639M, transaction and service plus interest income $174.093M.
A6: src_wh_volumes | B6: warehouse | D6: GEMI quarterly trading volume 2025: Q1 institutional $11.7B + retail $1.8B, Q2 $9.8B + $1.5B, Q3 $14.6B + ~$1.8B, Q4 $9.9B + $1.6B = $52.7B FY2025. Q3 and Q4 reconcile exactly to the $16.4B and $11.5B totals reported by the company.
A7: src_wh_mtu | B7: warehouse | D7: GEMI monthly_transacting_users: Q1 2025 502k, Q2 523k, Q3 587k, Q4 601k; Q1 2026 589k.
A8: src_wh_pred_tape | B8: warehouse | D8: RESULTS.EZ_METRICS.ez_gemini_predictions_metrics: 2,774,094 contracts traded 2025-12-15 to 2025-12-31; 119,336,290 in Q1 2026; 229,207,575 in Q2 2026. Contract count = $1-face USD notional.
A9: src_10q_q1_2026 | B9: 10-Q | C9: https://www.sec.gov/Archives/edgar/data/2055592/000205559226000050/R50.htm | D9: Transaction revenue - prediction market revenue: $444,000 for Q1 2026; exchange $17.2M; OTC $6.325M; service revenue $21.815M; total revenue $50.272M; operating expenses $144.460M.
A10: src_wh_comps | B10: warehouse | D10: Prediction venue fees over volume: Kalshi Q1 2026 $394.7M/$33.0B = 119.5 bps, Q2 2026 $671.0M/$65.7B = 102.1 bps; Polymarket Q1 5.8 bps, Q2 44.5 bps. Days 1-15 Gemini share of three-venue notional: 36.35 bps May, 20.46 bps June, 9.29 bps July.
A11: src_cex_tape | B11: warehouse | D11: PC_DBT_DB.PROD.fact_centralized_exchange_ohlcv_cleaned, gemini quote volume: Q4 2025 $10.52B, Q1 2026 $6.485B, Q2 2026 $4.403B, Jul 1-28 2026 $0.782B. Calibrates to reported volume at 1.09x and 0.97x in Q4 and Q1.
A12: src_wh_consensus | B12: warehouse | D12: GOLD.EQUITIES.FACT_EQUITIES_ESTIMATES, GEMI current consensus dated 2026-07-29: Q2 2026 total revenue $42.84M / EPS diluted -$0.690 / exchange $12.36M; FY2026 total revenue $193.18M / EPS -$2.897; FY2030 total revenue $394.15M / EPS -$1.775.
A13: src_wh_price | B13: warehouse | D13: GOLD.EQUITIES.GOLD_EQUITIES_PRICE_HISTORICAL_DATA: GEMI last close $4.065 on 2026-07-29.
A14: src_titan_volume_api | B14: exchange API | C14: https://api.gemini.com/v1/prediction-markets/volume/{date} | D14: Gemini Titan published daily prediction-market volume by category, one-sided. Full daily coverage from 2025-12-15. Q1 2026 59,667,196; Q2 2026 115,249,040; Jul 1-28 2026 45,646,530.
A15: src_titan_volume_spec | B15: docs | C15: https://developer.gemini.com/prediction-markets-spec/volume | D15: Endpoint spec. GET /v1/prediction-markets/volume/{date} and /hourly, unauthenticated, response is an array of {categoryPath, volume}. categoryPath is hierarchical, so only depth-1 rows may be summed.
A16: src_titan_rulebook | B16: rulebook | C16: https://www.cftc.gov/filings/orgrules/rules03252641973.pdf | D16: Gemini Titan LLC rulebook v1.8. Rule 2.17(b): Gemini shall make public on a daily basis information on settlement prices, volume, open interest and opening and closing ranges for actively traded Contracts.
A17: src_titan_exhibit_l | B17: CFTC filing | C17: https://www.cftc.gov/sites/default/files/filings/documents/2025/orgdcmgmniexhibitl250515.pdf | D17: Titan DCM application Exhibit L, Core Principle 8 Daily Publication of Trading Information.
A18: src_cftc_1601 | B18: regulation | C18: https://www.law.cornell.edu/cfr/text/17/16.01 | D18: 17 CFR 16.01. Paragraph (e) requires reporting markets to make volume, price and critical date information readily available to the news media and the general public without charge no later than the business day following. Transaction-level trade data is 16.02 and is not published.
A19: src_gemi_bs_q1_2026 | B19: 10-Q | C19: https://www.sec.gov/Archives/edgar/data/2055592/000205559226000050/R2.htm | D19: GEMI condensed consolidated balance sheet, Mar 31 2026, USD thousands: cash 215,623; restricted cash 103,747; customer custodial funds 483,774; crypto assets held 271,956; credit card receivables pledged 183,965; custodial funds due to customers 483,656; third party loans 75,349; related party loans 252,574; funding debt 140,457; lease liabilities 18,764; total liabilities 1,065,678; total assets 1,521,816; stockholders equity 456,138; intangibles 134,231.
A20: src_gemini_pred_fees | B20: fee schedule | C20: https://www.gemini.com/fees/predictions | D20: Gemini Predictions fees: Fee = Rate x Contracts x Price x (1 - Price), taker rate 0.07, maker rate 0.0175, no settlement fees.
A21: src_coingecko_gemini_vol | B21: market data | C21: https://api.coingecko.com/api/v3/exchanges/gemini/volume_chart | D21: Independent Gemini spot exchange volume. Q1 2026 $62.7M/day, Q2 2026 $37.5M/day, Jul 1-28 2026 $23.0M/day, July versus Q2 -38.7%.
A22: src_hood_q2_2026 | B22: press release | C22: https://investors.robinhood.com/news-releases | D22: Robinhood Q2 2026, reported 2026-07-29: total net revenues $1.31B, crypto revenue $100M down 38% YoY, event contracts revenue $156M up over 10x, event contracts traded 13.6B, crypto notional $40B (app $18B, Bitstamp $22B), net income $573M, diluted EPS $0.62.
